QSAR/QSAR_Dataset.py
QSAR/QSAR_Inference.py
QSAR/QSAR_Loss.py
QSAR/QSAR_Models.py
QSAR/QSAR_Train.py
QSAR/QSAR_Utils.py
QSAR/__init__.py
QSAR/main.py
QSAR-0.0.2.dist-info/LICENSE
QSAR-0.0.2.dist-info/METADATA
QSAR-0.0.2.dist-info/WHEEL
QSAR-0.0.2.dist-info/top_level.txt
QSAR-0.0.2.dist-info/RECORD
