Metadata-Version: 2.1
Name: QSAR
Version: 0.0.2
Summary: Python library for QSAR model from Juvena Machine Learning Team.
Home-page: UNKNOWN
Author: Xi Chen, Tara Paglino
Author-email: billchenxi@gmail.com, tarapaglino@gmail.com
License: UNKNOWN
Keywords: QSAR
Platform: any
Classifier: Programming Language :: Python :: 3
Classifier: License :: OSI Approved :: GNU Lesser General Public License v3 or later (LGPLv3+)
Classifier: Operating System :: OS Independent
Requires-Python: >=3.6
